bqslots/__init__.py
bqslots/box_print.py
bqslots/lock.py
bqslots/slots_allocation.py
bqslots-0.1.3.dist-info/LICENSE
bqslots-0.1.3.dist-info/METADATA
bqslots-0.1.3.dist-info/WHEEL
bqslots-0.1.3.dist-info/dependency_links.txt
bqslots-0.1.3.dist-info/top_level.txt
bqslots-0.1.3.dist-info/RECORD
