Metadata-Version: 2.1
Name: bqslots
Version: 0.1.3
Summary: A small wrapper for bigquery slot allocaiton
Home-page: https://github.com/connor-ps/bqslots
Author: connor
Author-email: connor.mcshane@paymentsense.com
License: MIT license
Keywords: bqslots
Platform: UNKNOWN
Classifier: Development Status :: 2 - Pre-Alpha
Classifier: Intended Audience :: Developers
Classifier: License :: OSI Approved :: MIT License
Classifier: Natural Language :: English
Classifier: Programming Language :: Python :: 3
Classifier: Programming Language :: Python :: 3.7
Classifier: Programming Language :: Python :: 3.8
Classifier: Programming Language :: Python :: 3.9
Requires-Python: >=3.7
License-File: LICENSE
Requires-Dist: google-cloud-bigquery-reservation (==1.6.0)
Requires-Dist: backoff (==1.11.1)
Requires-Dist: google-cloud-storage (==1.31.0)
Requires-Dist: pytz
